{
    "metadata": {
        "id": 1097373587,
        "node_id": "R_kgDOQWiXkw",
        "name": "epstein-archive",
        "full_name": "ErikVeland/epstein-archive",
        "private": false,
        "owner": {
            "login": "ErikVeland",
            "id": 251715,
            "node_id": "MDQ6VXNlcjI1MTcxNQ==",
            "avatar_url": "https://avatars.githubusercontent.com/u/251715?v=4",
            "gravatar_id": "",
            "url": "https://api.github.com/users/ErikVeland",
            "html_url": "https://github.com/ErikVeland",
            "followers_url": "https://api.github.com/users/ErikVeland/followers",
            "following_url": "https://api.github.com/users/ErikVeland/following{/other_user}",
            "gists_url": "https://api.github.com/users/ErikVeland/gists{/gist_id}",
            "starred_url": "https://api.github.com/users/ErikVeland/starred{/owner}{/repo}",
            "subscriptions_url": "https://api.github.com/users/ErikVeland/subscriptions",
            "organizations_url": "https://api.github.com/users/ErikVeland/orgs",
            "repos_url": "https://api.github.com/users/ErikVeland/repos",
            "events_url": "https://api.github.com/users/ErikVeland/events{/privacy}",
            "received_events_url": "https://api.github.com/users/ErikVeland/received_events",
            "type": "User",
            "user_view_type": "public",
            "site_admin": false
        },
        "html_url": "https://github.com/ErikVeland/epstein-archive",
        "description": "Epstein Files Archive - Document processing and analysis system for Epstein files with spice ratings, entity extraction, and advanced search capabilities",
        "fork": false,
        "url": "https://api.github.com/repos/ErikVeland/epstein-archive",
        "forks_url": "https://api.github.com/repos/ErikVeland/epstein-archive/forks",
        "keys_url": "https://api.github.com/repos/ErikVeland/epstein-archive/keys{/key_id}",
        "collaborators_url": "https://api.github.com/repos/ErikVeland/epstein-archive/collaborators{/collaborator}",
        "teams_url": "https://api.github.com/repos/ErikVeland/epstein-archive/teams",
        "hooks_url": "https://api.github.com/repos/ErikVeland/epstein-archive/hooks",
        "issue_events_url": "https://api.github.com/repos/ErikVeland/epstein-archive/issues/events{/number}",
        "events_url": "https://api.github.com/repos/ErikVeland/epstein-archive/events",
        "assignees_url": "https://api.github.com/repos/ErikVeland/epstein-archive/assignees{/user}",
        "branches_url": "https://api.github.com/repos/ErikVeland/epstein-archive/branches{/branch}",
        "tags_url": "https://api.github.com/repos/ErikVeland/epstein-archive/tags",
        "blobs_url": "https://api.github.com/repos/ErikVeland/epstein-archive/git/blobs{/sha}",
        "git_tags_url": "https://api.github.com/repos/ErikVeland/epstein-archive/git/tags{/sha}",
        "git_refs_url": "https://api.github.com/repos/ErikVeland/epstein-archive/git/refs{/sha}",
        "trees_url": "https://api.github.com/repos/ErikVeland/epstein-archive/git/trees{/sha}",
        "statuses_url": "https://api.github.com/repos/ErikVeland/epstein-archive/statuses/{sha}",
        "languages_url": "https://api.github.com/repos/ErikVeland/epstein-archive/languages",
        "stargazers_url": "https://api.github.com/repos/ErikVeland/epstein-archive/stargazers",
        "contributors_url": "https://api.github.com/repos/ErikVeland/epstein-archive/contributors",
        "subscribers_url": "https://api.github.com/repos/ErikVeland/epstein-archive/subscribers",
        "subscription_url": "https://api.github.com/repos/ErikVeland/epstein-archive/subscription",
        "commits_url": "https://api.github.com/repos/ErikVeland/epstein-archive/commits{/sha}",
        "git_commits_url": "https://api.github.com/repos/ErikVeland/epstein-archive/git/commits{/sha}",
        "comments_url": "https://api.github.com/repos/ErikVeland/epstein-archive/comments{/number}",
        "issue_comment_url": "https://api.github.com/repos/ErikVeland/epstein-archive/issues/comments{/number}",
        "contents_url": "https://api.github.com/repos/ErikVeland/epstein-archive/contents/{+path}",
        "compare_url": "https://api.github.com/repos/ErikVeland/epstein-archive/compare/{base}...{head}",
        "merges_url": "https://api.github.com/repos/ErikVeland/epstein-archive/merges",
        "archive_url": "https://api.github.com/repos/ErikVeland/epstein-archive/{archive_format}{/ref}",
        "downloads_url": "https://api.github.com/repos/ErikVeland/epstein-archive/downloads",
        "issues_url": "https://api.github.com/repos/ErikVeland/epstein-archive/issues{/number}",
        "pulls_url": "https://api.github.com/repos/ErikVeland/epstein-archive/pulls{/number}",
        "milestones_url": "https://api.github.com/repos/ErikVeland/epstein-archive/milestones{/number}",
        "notifications_url": "https://api.github.com/repos/ErikVeland/epstein-archive/notifications{?since,all,participating}",
        "labels_url": "https://api.github.com/repos/ErikVeland/epstein-archive/labels{/name}",
        "releases_url": "https://api.github.com/repos/ErikVeland/epstein-archive/releases{/id}",
        "deployments_url": "https://api.github.com/repos/ErikVeland/epstein-archive/deployments",
        "created_at": "2025-11-16T03:37:54Z",
        "updated_at": "2026-02-23T13:45:50Z",
        "pushed_at": "2026-02-23T13:45:46Z",
        "git_url": "git://github.com/ErikVeland/epstein-archive.git",
        "ssh_url": "git@github.com:ErikVeland/epstein-archive.git",
        "clone_url": "https://github.com/ErikVeland/epstein-archive.git",
        "svn_url": "https://github.com/ErikVeland/epstein-archive",
        "homepage": null,
        "size": 760005,
        "stargazers_count": 38,
        "watchers_count": 38,
        "language": "TypeScript",
        "has_issues": true,
        "has_projects": true,
        "has_downloads": true,
        "has_wiki": true,
        "has_pages": false,
        "has_discussions": false,
        "forks_count": 14,
        "mirror_url": null,
        "archived": false,
        "disabled": false,
        "open_issues_count": 3,
        "license": null,
        "allow_forking": true,
        "is_template": false,
        "web_commit_signoff_required": false,
        "has_pull_requests": true,
        "pull_request_creation_policy": "all",
        "topics": [],
        "visibility": "public",
        "forks": 14,
        "open_issues": 3,
        "watchers": 38,
        "default_branch": "main",
        "permissions": {
            "admin": false,
            "maintain": false,
            "push": false,
            "triage": false,
            "pull": true
        },
        "score": 1.0
    },
    "readme_content": "<p align=\"center\">\n  <img src=\"logo.png\" alt=\"Epstein Archive\" width=\"400\">\n</p>\n\n<h1 align=\"center\">Epstein Archive</h1>\n\n<p align=\"center\">\n  <strong>A comprehensive investigative research platform</strong> for analyzing and cross-referencing documents, entities, and relationships from the Epstein Files corpus.\n</p>\n\n<p align=\"center\">\n  <a href=\"https://epstein.academy\"><img src=\"https://img.shields.io/badge/\ud83c\udf10_LIVE_SITE-epstein.academy-blue?style=for-the-badge&logo=data:image/svg+xml;base64,PHN2ZyB4bWxucz0iaHR0cDovL3d3dy53My5vcmcvMjAwMC9zdmciIHdpZHRoPSIyNCIgaGVpZ2h0PSIyNCIgdmlld0JveD0iMCAwIDI0IDI0IiBmaWxsPSJub25lIiBzdHJva2U9IndoaXRlIiBzdHJva2Utd2lkdGg9IjIiIHN0cm9rZS1saW5lY2FwPSJyb3VuZCIgc3Ryb2tlLWxpbmVqb2luPSJyb3VuZCI+PGNpcmNsZSBjeD0iMTIiIGN5PSIxMiIgcj0iMTAiPjwvY2lyY2xlPjxsaW5lIHgxPSIyIiB5MT0iMTIiIHgyPSIyMiIgeTI9IjEyIj48L2xpbmU+PHBhdGggZD0iTTEyIDJhMTUuMyAxNS4zIDAgMCAxIDQgMTAgMTUuMyAxNS4zIDAgMCAxLTQgMTAgMTUuMyAxNS4zIDAgMCAxLTQtMTAgMTUuMyAxNS4zIDAgMCAxIDQtMTB6Ij48L3BhdGg+PC9zdmc+\" alt=\"Live Site\"></a>\n</p>\n\n---\n\n## \ud83d\ude80 Quick Start\n\n### Prerequisites\n\n- Node.js v18+\n- SQLite3\n- pnpm\n\n### Installation\n\n```bash\n# Clone and install\ngit clone <repo-url>\ncd epstein-archive\npnpm install\n\n# Setup Database (Scenario A: Sample Data)\n# Points to the included sample.db (~50 docs, ~130 entities)\necho \"DB_PATH=./sample.db\" > .env.local\n\n# Scenario B: Full Ingestion (Requires 300GB+ SSD)\n# See TECHNICAL_OVERVIEW.md for pipeline details\n\n# Start development server\npnpm dev\n```\n\n### Production Build\n\n```bash\n# Build for production\npnpm build:prod\n\n# Start production server\npnpm start\n```\n\n## \u2728 Features\n\n- [x] **86,000+ Entities** with relationship mapping and risk scoring\n- [x] **51,000+ Documents** with full-text search and integrated PDF viewing\n- [x] **500+ Verified Media Files** (Photos, Videos, Audio)\n- [x] **Interactive Visualization**: Force-directed network graphs, timelines, and geospatial maps\n- [x] **Forensic Tools**: Chain of custody tracking, red flag index, and hypothesis testing\n- [x] **Admin Dashboard**: User management, audit logs, and system health monitoring\n\n## \ud83d\udcda Documentation\n\n- [**Wiki & Architecture**](docs/wiki.md) - Core system architecture and logic\n- [**User Guide**](docs/wiki-user-guide.md) - End-user manual\n- [**API Reference**](docs/API.md) - REST API endpoints\n- [**Data Governance**](docs/data-governance-standards.md) - Standards for data integrity and privacy\n- [**User Journey**](docs/user-journey-mapping.md) - UX analysis\n- [**Technical Reference**](docs/technical-reference.md) - Deep dive for developers\n\n## \ud83d\udee0\ufe0f Deployment\n\nThe project includes a robust deployment script `deploy.sh` that handles:\n\n1.  **Verification**: Checks schema integrity and configuration.\n2.  **Backup**: Creates remote backups of code and database.\n3.  **Deployment**: Uploads, installs dependencies, and restarts services.\n4.  **Health Check**: Verifies critical endpoints post-deployment.\n\n```bash\n# Deploy to production\n./deploy.sh\n```\n\n## \ud83d\udcc2 Project Structure\n\n```\nepstein-archive/\n\u251c\u2500\u2500 src/\n\u2502   \u251c\u2500\u2500 components/         # React UI components\n\u2502   \u251c\u2500\u2500 pages/              # Application pages (AdminDashboard, etc.)\n\u2502   \u251c\u2500\u2500 services/           # Frontend API services\n\u2502   \u251c\u2500\u2500 server/             # Express backend & API routes\n\u2502   \u2514\u2500\u2500 scripts/            # Type-safe utility scripts\n\u251c\u2500\u2500 scripts/                # Shell and maintenance scripts\n\u251c\u2500\u2500 docs/                   # Documentation\n\u251c\u2500\u2500 data/                   # Raw media and OCR data (gitignored)\n\u2514\u2500\u2500 public/                 # Static assets\n```\n\n## \u2696\ufe0f License\n\nThis project is for research and educational purposes only.\n"
}